weiqi/__init__.py
weiqi/core/board.py
weiqi/core/figure.py
weiqi/core/game.py
weiqi/core/group.py
weiqi/core/move.py
weiqi/core/position.py
weiqi/exceptions/__init__.py
weiqi/exceptions/game.py
weiqi/players/bot.py
weiqi/players/player.py
weiqi/utils/enums.py
weiqi/utils/game_status.py
weiqi-0.2.1.dist-info/METADATA
weiqi-0.2.1.dist-info/WHEEL
weiqi-0.2.1.dist-info/RECORD
