Metadata-Version: 2.1
Name: weiqi
Version: 0.2.1
Summary: A simple Weiqi (Go) library for Python
Author: Roman505050
Author-email: myhun59@gmail.com
Requires-Python: >=3.11,<3.13
Classifier: Programming Language :: Python :: 3
Classifier: Programming Language :: Python :: 3.11
Classifier: Programming Language :: Python :: 3.12
